plox/__init__.py
plox/param.py
plox/param_make.py
plox/plox.py
plox-0.0.3.dist-info/LICENSE
plox-0.0.3.dist-info/METADATA
plox-0.0.3.dist-info/WHEEL
plox-0.0.3.dist-info/top_level.txt
plox-0.0.3.dist-info/RECORD
