Metadata-Version: 2.1
Name: plox
Version: 0.0.3
Summary: Context manager for matplotlib figures
Home-page: https://github.com/numpde/plox
Author: RA
Author-email: numpde@null.net
License: UNKNOWN
Keywords: development matplotlib figure context
Platform: UNKNOWN
Classifier: Intended Audience :: Developers
Classifier: Programming Language :: Python :: 3
Classifier: License :: OSI Approved :: MIT License
Classifier: Operating System :: OS Independent
Requires-Python: >=3.6
Requires-Dist: matplotlib
